docker_analyzer/__init__.py
docker_analyzer/analysis.py
docker_analyzer/cleaning.py
docker_analyzer/cli/cli.py
docker_analyzer/cli/compare.py
docker_analyzer/cli/inspect_image.py
docker_analyzer/cli/utils.py
docker_analyzer/comparer.py
docker_analyzer/config.py
docker_analyzer/defaults_utils.py
docker_analyzer/docker_interaction.py
docker_analyzer/gui/__init__.py
docker_analyzer/gui/routes.py
docker_analyzer/gui/static/css/dataframe_styles.css
docker_analyzer/gui/static/css/styles.css
docker_analyzer/gui/static/favicon.ico
docker_analyzer/gui/templates/404.html
docker_analyzer/gui/templates/footer.html
docker_analyzer/gui/templates/header.html
docker_analyzer/gui/templates/index.html
docker_analyzer/gui/templates/results.html
docker_analyzer/gui/views_data.py
docker_analyzer/inspection.py
docker_analyzer/inspection_io.py
docker_analyzer/logger.py
docker_analyzer/python:3.9-slim.json
docker_analyzer/python:3.9.json
docker_analyzer/utils.py
docker_analyzer-0.1.3.dist-info/LICENSE
docker_analyzer-0.1.3.dist-info/METADATA
docker_analyzer-0.1.3.dist-info/WHEEL
docker_analyzer-0.1.3.dist-info/entry_points.txt
docker_analyzer-0.1.3.dist-info/RECORD
