Metadata-Version: 2.1
Name: docker_analyzer
Version: 0.1.3
Summary: A lightweight to tool to analyse and compare Docker images instantly, focusing on layer analysis
Author: Gianfrancesco Angelini
Author-email: gian.angelini@hotmail.com
Requires-Python: >=3.10,<3.14
Classifier: Programming Language :: Python :: 3
Classifier: Programming Language :: Python :: 3.10
Classifier: Programming Language :: Python :: 3.11
Classifier: Programming Language :: Python :: 3.12
Classifier: Programming Language :: Python :: 3.13
Requires-Dist: anytree (>=2.12.1,<3.0.0)
Requires-Dist: beautifulsoup4 (>=4.12.3,<5.0.0)
Requires-Dist: docker (>=7.1.0,<8.0.0)
Requires-Dist: flask (>=3.0.3,<4.0.0)
Requires-Dist: inquirerpy (>=0.3.4,<0.4.0)
Requires-Dist: keyboard (>=0.13.5,<0.14.0)
Requires-Dist: numpy (>=2.1.1,<3.0.0)
Requires-Dist: pandas (>=2.2.2,<3.0.0)
Requires-Dist: pyyaml (>=6.0.2,<7.0.0)
Requires-Dist: rich (>=13.8.1,<14.0.0)
Requires-Dist: textual (>=0.79.1,<0.80.0)
Requires-Dist: toml (>=0.10.2,<0.11.0)
Requires-Dist: urwid (>=2.6.15,<3.0.0)
